setup.py
all_the_chatbots/__init__.py
all_the_chatbots/botlibre.py
all_the_chatbots/catty.py
all_the_chatbots/chatterer.py
all_the_chatbots/nameguru.py
all_the_chatbots/pandorabots.py
all_the_chatbots/peninsulabahai.py
all_the_chatbots/qaqash.py
all_the_chatbots/wolframalpha.py
all_the_chatbots.egg-info/PKG-INFO
all_the_chatbots.egg-info/SOURCES.txt
all_the_chatbots.egg-info/dependency_links.txt
all_the_chatbots.egg-info/requires.txt
all_the_chatbots.egg-info/top_level.txt