Metadata-Version: 1.0
Name: all-the-chatbots
Version: 0.2.1
Summary: unofficial apis for all the chatbots
Home-page: https://github.com/OpenJarbas/all_the_chatbots
Author: jarbasAI
Author-email: jarbasai@mailfence.com
License: MIT
Platform: UNKNOWN
